simnexus/__init__.py
simnexus-0.3.1.dist-info/licenses/LICENSE
simnexus-0.3.1.dist-info/METADATA
simnexus-0.3.1.dist-info/WHEEL
simnexus-0.3.1.dist-info/top_level.txt
simnexus-0.3.1.dist-info/RECORD
