Metadata-Version: 2.4
Name: simnexus
Version: 0.3.1
Summary: DEPRECATED: Please use sim-lab instead
Home-page: https://github.com/michael/simnexus
Author: Michael
License-Expression: MIT
Requires-Python: >=3.7
License-File: LICENSE
Dynamic: author
Dynamic: home-page
Dynamic: license-file
Dynamic: requires-python
